{".class": "MypyFile", "_fullname": "coursera_symmetricalNum", "is_partial_stub_package": false, "is_stub": false, "names": {".class": "SymbolTable", "__doc__": {".class": "SymbolTableNode", "kind": "Gdef", "node": {".class": "Var", "flags": ["is_ready"], "fullname": "coursera_symmetricalNum.__doc__", "name": "__doc__", "type": "builtins.str"}}, "__file__": {".class": "SymbolTableNode", "kind": "Gdef", "node": {".class": "Var", "flags": ["is_ready"], "fullname": "coursera_symmetricalNum.__file__", "name": "__file__", "type": "builtins.str"}}, "__name__": {".class": "SymbolTableNode", "kind": "Gdef", "node": {".class": "Var", "flags": ["is_ready"], "fullname": "coursera_symmetricalNum.__name__", "name": "__name__", "type": "builtins.str"}}, "__package__": {".class": "SymbolTableNode", "kind": "Gdef", "node": {".class": "Var", "flags": ["is_ready"], "fullname": "coursera_symmetricalNum.__package__", "name": "__package__", "type": "builtins.str"}}, "n": {".class": "SymbolTableNode", "kind": "Gdef", "node": {".class": "Var", "flags": [], "fullname": "coursera_symmetricalNum.n", "name": "n", "type": "builtins.int"}}, "n1": {".class": "SymbolTableNode", "kind": "Gdef", "node": {".class": "Var", "flags": [], "fullname": "coursera_symmetricalNum.n1", "name": "n1", "type": "builtins.int"}}, "n2": {".class": "SymbolTableNode", "kind": "Gdef", "node": {".class": "Var", "flags": [], "fullname": "coursera_symmetricalNum.n2", "name": "n2", "type": "builtins.int"}}, "n3": {".class": "SymbolTableNode", "kind": "Gdef", "node": {".class": "Var", "flags": [], "fullname": "coursera_symmetricalNum.n3", "name": "n3", "type": "builtins.int"}}, "n4": {".class": "SymbolTableNode", "kind": "Gdef", "node": {".class": "Var", "flags": [], "fullname": "coursera_symmetricalNum.n4", "name": "n4", "type": "builtins.int"}}}, "path": "/Users/olgakozlenkova/Documents/Projects/learn_programming/learn_python/week1/coursera_symmetricalNum.py"}